<?xml version="1.0" encoding="UTF-8"?>
<!DOCTYPE mapper PUBLIC "-//mybatis.org//DTD Mapper 3.0//EN" "http://mybatis.org/dtd/mybatis-3-mapper.dtd">
<mapper namespace="com.ten.ParkNShop.mapper.ADMapper">
  <resultMap id="BaseResultMap" type="com.ten.ParkNShop.entity.AD">
    <!--
      WARNING - @mbggenerated
      This element is automatically generated by MyBatis Generator, do not modify.
    -->
    <id column="ADId" jdbcType="INTEGER" property="adId" />
    <result column="ADType" jdbcType="INTEGER" property="adType" />
    <result column="ADStatus" jdbcType="INTEGER" property="adStatus" />
    <result column="otherId" jdbcType="INTEGER" property="otherId" />
    <result column="adminId" jdbcType="INTEGER" property="adminId" />
    <result column="ADName" jdbcType="VARCHAR" property="adName" />
    <result column="ADPhotoUrl" jdbcType="VARCHAR" property="adPhotoUrl" />
    <result column="ADDescription" jdbcType="VARCHAR" property="adDescription" />
    <result column="ADPrice" jdbcType="REAL" property="adPrice" />
    <result column="ADStartDate" jdbcType="TIMESTAMP" property="adStartDate" />
    <result column="ADTime" jdbcType="INTEGER" property="adTime" />
  </resultMap>
  <sql id="Base_Column_List">
    <!--
      WARNING - @mbggenerated
      This element is automatically generated by MyBatis Generator, do not modify.
    -->
    ADId, ADType, ADStatus, otherId, adminId, ADName, ADPhotoUrl,  ADDescription,
    ADPrice, ADStartDate, ADTime
  </sql>
  <select id="selectByPrimaryKey" parameterType="java.lang.Integer" resultMap="BaseResultMap">
    <!--
      WARNING - @mbggenerated
      This element is automatically generated by MyBatis Generator, do not modify.
    -->
    select 
    <include refid="Base_Column_List" />
    from ad
    where ADId = #{adId,jdbcType=INTEGER}
  </select>
  <delete id="deleteByPrimaryKey" parameterType="java.lang.Integer">
    <!--
      WARNING - @mbggenerated
      This element is automatically generated by MyBatis Generator, do not modify.
    -->
    delete from ad
    where ADId = #{adId,jdbcType=INTEGER}
  </delete>
  <insert id="insert" parameterType="com.ten.ParkNShop.entity.AD">
    <!--
      WARNING - @mbggenerated
      This element is automatically generated by MyBatis Generator, do not modify.
    -->
    insert into ad (ADId, ADType, ADStatus, 
      otherId, adminId, ADName, 
      ADPhotoUrl, ADDescription,
      ADPrice, ADStartDate, ADTime
      )
    values (#{adId,jdbcType=INTEGER}, #{adType,jdbcType=INTEGER}, #{adStatus,jdbcType=INTEGER}, 
      #{otherId,jdbcType=INTEGER}, #{adminId,jdbcType=INTEGER}, #{adName,jdbcType=VARCHAR}, 
      #{adPhotoUrl,jdbcType=VARCHAR}, #{addescription,jdbcType=VARCHAR},
      #{adprice,jdbcType=REAL}, #{adstartdate,jdbcType=TIMESTAMP}, #{adtime,jdbcType=INTEGER}
      )
  </insert>
  <insert id="insertSelective" parameterType="com.ten.ParkNShop.entity.AD">
    <!--
      WARNING - @mbggenerated
      This element is automatically generated by MyBatis Generator, do not modify.
    -->
    insert into ad
    <trim prefix="(" suffix=")" suffixOverrides=",">
      <if test="adId != null">
        ADId,
      </if>
      <if test="adType != null">
        ADType,
      </if>
      <if test="adStatus != null">
        ADStatus,
      </if>
      <if test="otherId != null">
        otherId,
      </if>
      <if test="adminId != null">
        adminId,
      </if>
      <if test="adName != null">
        ADName,
      </if>
      <if test="adPhotoUrl != null">
        ADPhotoUrl,
      </if>
      <if test="adDescription != null">
        ADDescription,
      </if>
      <if test="adprice != null">
        ADPrice,
      </if>
      <if test="adstartdate != null">
        ADStartDate,
      </if>
      <if test="adtime != null">
        ADTime,
      </if>
    </trim>
    <trim prefix="values (" suffix=")" suffixOverrides=",">
      <if test="adId != null">
        #{adId,jdbcType=INTEGER},
      </if>
      <if test="adType != null">
        #{adType,jdbcType=INTEGER},
      </if>
      <if test="adStatus != null">
        #{adStatus,jdbcType=INTEGER},
      </if>
      <if test="otherId != null">
        #{otherId,jdbcType=INTEGER},
      </if>
      <if test="adminId != null">
        #{adminId,jdbcType=INTEGER},
      </if>
      <if test="adName != null">
        #{adName,jdbcType=VARCHAR},
      </if>
      <if test="adPhotoUrl != null">
        #{adPhotoUrl,jdbcType=VARCHAR},
      </if>
      <if test="addescription != null">
        #{addescription,jdbcType=VARCHAR},
      </if>
      <if test="adprice != null">
        #{adprice,jdbcType=REAL},
      </if>
      <if test="adstartdate != null">
        #{adstartdate,jdbcType=TIMESTAMP},
      </if>
      <if test="adtime != null">
        #{adtime,jdbcType=INTEGER},
      </if>
    </trim>
  </insert>
  <update id="updateByPrimaryKeySelective" parameterType="com.ten.ParkNShop.entity.AD">
    <!--
      WARNING - @mbggenerated
      This element is automatically generated by MyBatis Generator, do not modify.
    -->
    update ad
    <set>
      <if test="adType != null">
        ADType = #{adType,jdbcType=INTEGER},
      </if>
      <if test="adStatus != null">
        ADStatus = #{adStatus,jdbcType=INTEGER},
      </if>
      <if test="otherId != null">
        otherId = #{otherId,jdbcType=INTEGER},
      </if>
      <if test="adminId != null">
        adminId = #{adminId,jdbcType=INTEGER},
      </if>
      <if test="adName != null">
        ADName = #{adName,jdbcType=VARCHAR},
      </if>
      <if test="adPhotoUrl != null">
        ADPhotoUrl = #{adPhotoUrl,jdbcType=VARCHAR},
      </if>
      <if test="adDescription != null">
        ADDescription = #{addescription,jdbcType=VARCHAR},
      </if>
      <if test="adPrice != null">
        ADPrice = #{adprice,jdbcType=REAL},
      </if>
      <if test="adStartDate != null">
        ADStartDate = #{adstartdate,jdbcType=TIMESTAMP},
      </if>
      <if test="adTime != null">
        ADTime = #{adtime,jdbcType=INTEGER},
      </if>
    </set>
    where ADId = #{adId,jdbcType=INTEGER}
  </update>
  <update id="updateByPrimaryKey" parameterType="com.ten.ParkNShop.entity.AD">
    <!--
      WARNING - @mbggenerated
      This element is automatically generated by MyBatis Generator, do not modify.
    -->
    update ad
    set ADType = #{adType,jdbcType=INTEGER},
      ADStatus = #{adStatus,jdbcType=INTEGER},
      otherId = #{otherId,jdbcType=INTEGER},
      adminId = #{adminId,jdbcType=INTEGER},
      ADName = #{adName,jdbcType=VARCHAR},
      ADPhotoUrl = #{adPhotoUrl,jdbcType=VARCHAR},
      ADDescription = #{adDescription,jdbcType=VARCHAR},
      ADPrice = #{adPrice,jdbcType=REAL},
      ADStartDate = #{adStartDate,jdbcType=TIMESTAMP},
      ADTime = #{adTime,jdbcType=INTEGER}
    where ADId = #{adId,jdbcType=INTEGER}
  </update>

  <select id="selectADByOtherId" parameterType="java.lang.Integer" resultMap="BaseResultMap">
    select
    <include refid="Base_Column_List" />
    from ad
    where sellerId=#{sellerId}
  </select>

  <select id="selectADByADType" parameterType="java.lang.String" resultMap="BaseResultMap">
    select
    <include refid="Base_Column_List" />
    from ad
    where ADType=#{adType}
  </select>

  <select id="selectADByADStatus" parameterType="java.lang.String" resultMap="BaseResultMap">
    select
    <include refid="Base_Column_List" />
    from ad
    where adStatus=#{adStatus}
  </select>

  <select id="selectADTop10Product" resultMap="BaseResultMap">
    select
    <include refid="Base_Column_List" />
    from ad
    where adType="1" and ADStatus="2"
    ORDER BY ADPrice
    LIMIT 0, 10
  </select>

  <select id="selectADTop5Store" resultMap="BaseResultMap">
  select
  <include refid="Base_Column_List" />
  from ad
  where adType="2" and ADStatus="2"
  ORDER BY ADPrice
  LIMIT 0, 10
</select>

  <select id="selectAllAD" parameterType="java.lang.Integer" resultMap="BaseResultMap">
    select
    <include refid="Base_Column_List" />
    from ad
    LIMIT #{start}, #{pageSize}
  </select>

  <select id="selectShopAD" parameterType="java.lang.Integer" resultMap="BaseResultMap">
    select
    *
    from ad
    where otherId = #{sellerId} and ADType = 2
  </select>

  <select id="selectProductAD" parameterType="java.lang.Integer" resultMap="BaseResultMap">
    select
    *
    from ad
    where ADType IN (1,3,4) and otherId IN
    	(select
			 productId
	     from
			 product
	     where
			 sellerId = #{sellerId})
  </select>
  

</mapper>